decorated_router/__init__.py
decorated_router/admin.py
decorated_router/apps.py
decorated_router/models.py
decorated_router/tests.py
decorated_router/views.py
decorated_router/api/__init__.py
decorated_router/api/api.py
decorated_router/api/decorators.py
decorated_router/management/__init__.py
decorated_router/migrations/__init__.py
decorated_router/tests/__init__.py
decorated_router/tests/settings.py
decorated_router/tests/test_api.py
decorated_router/tests/assets/__init__.py
decorated_router/tests/assets/blog.py
decorated_router/tests/assets/products.py
decorated_router/tests/assets/users/__init__.py
decorated_router/tests/assets/users/login.py
decorated_router/tests/assets/users/logout.py
decorated_router/tests/assets/users/permissions.py
django_decorated_routes-0.0.2.dist-info/METADATA
django_decorated_routes-0.0.2.dist-info/WHEEL
django_decorated_routes-0.0.2.dist-info/top_level.txt
django_decorated_routes-0.0.2.dist-info/RECORD
