Metadata-Version: 2.1
Name: django-decorated-routes
Version: 0.0.2
Summary: Auto registering routes in Django
Home-page: https://github.com/RoySegall/django-decorated-router
Author: Roy Segall
Author-email: roy@segall.io
License: MIT
Platform: UNKNOWN
